{
  "name": "@energyweb/semantic-release-config",
  "entries": [
    {
      "version": "1.0.2",
      "tag": "@energyweb/semantic-release-config_v1.0.2",
      "date": "Fri, 25 Feb 2022 12:12:27 GMT",
      "comments": {
        "patch": [
          {
            "comment": "remove `dist` dir from GH release assets"
          }
        ]
      }
    },
    {
      "version": "1.0.1",
      "tag": "@energyweb/semantic-release-config_v1.0.1",
      "date": "Fri, 25 Feb 2022 09:05:40 GMT",
      "comments": {
        "patch": [
          {
            "comment": "release fixed pacakge"
          }
        ]
      }
    }
  ]
}
